haiku/__init__.py
haiku/gac.py
haiku/haiku.py
haiku/analyzer/__init__.py
haiku/analyzer/analyzer_impl.py
haiku/analyzer/selector.py
haiku/classifier/__init__.py
haiku/classifier/classifier_impl.py
haiku/classifier/grid.py
haiku/classifier/learner/Makefile
haiku/classifier/learner/__init__.py
haiku/classifier/learner/learner_impl.py
haiku/classifier/learner/test.cpp
haiku/classifier/learner/util.c
haiku/classifier/learner/liblinear/COPYRIGHT
haiku/classifier/learner/liblinear/Makefile
haiku/classifier/learner/liblinear/Makefile.win
haiku/classifier/learner/liblinear/README
haiku/classifier/learner/liblinear/heart_scale
haiku/classifier/learner/liblinear/linear.cpp
haiku/classifier/learner/liblinear/linear.def
haiku/classifier/learner/liblinear/linear.h
haiku/classifier/learner/liblinear/predict.c
haiku/classifier/learner/liblinear/train.c
haiku/classifier/learner/liblinear/tron.cpp
haiku/classifier/learner/liblinear/tron.h
haiku/classifier/learner/liblinear/blas/Makefile
haiku/classifier/learner/liblinear/blas/blas.h
haiku/classifier/learner/liblinear/blas/blasp.h
haiku/classifier/learner/liblinear/blas/daxpy.c
haiku/classifier/learner/liblinear/blas/ddot.c
haiku/classifier/learner/liblinear/blas/dnrm2.c
haiku/classifier/learner/liblinear/blas/dscal.c
haiku/classifier/learner/liblinear/python/Makefile
haiku/classifier/learner/liblinear/python/README
haiku/classifier/learner/liblinear/python/liblinear.py
haiku/classifier/learner/liblinear/python/liblinearutil.py
haiku/classifier/learner/liblinear/windows/liblinear.dll
haiku/classifier/learner/liblinear/windows/liblinear.exp
haiku/classifier/learner/liblinear/windows/liblinear.lib
haiku/classifier/learner/liblinear/windows/libsvmread.mexw64
haiku/classifier/learner/liblinear/windows/libsvmwrite.mexw64
haiku/classifier/learner/liblinear/windows/predict.exe
haiku/classifier/learner/liblinear/windows/predict.mexw64
haiku/classifier/learner/liblinear/windows/train.exe
haiku_lst-0.1.dist-info/DESCRIPTION.rst
haiku_lst-0.1.dist-info/METADATA
haiku_lst-0.1.dist-info/RECORD
haiku_lst-0.1.dist-info/WHEEL
haiku_lst-0.1.dist-info/metadata.json
haiku_lst-0.1.dist-info/top_level.txt
