Metadata-Version: 2.0
Name: haiku-lst
Version: 0.1
Summary: UNKNOWN
Home-page: https://gitlab.com/hansroh/haiku
Author: Hans Roh
Author-email: hansroh@gmail.com
License: UNKNOWN
Platform: posix
Platform: nt
Requires-Dist: delune
